WebHarvester/__init__.py
WebHarvester/collector.py
WebHarvester/counter.py
WebHarvester/dispatcher.py
WebHarvester/engine.py
WebHarvester/loader.py
WebHarvester/logger_ex.py
WebHarvester/processor.py
WebHarvester/request.py
WebHarvester/response.py
WebHarvester/settings.py
WebHarvester/spider.py
WebHarvester/update.py
WebHarvester-0.1.1.dist-info/LICENSE
WebHarvester-0.1.1.dist-info/METADATA
WebHarvester-0.1.1.dist-info/WHEEL
WebHarvester-0.1.1.dist-info/top_level.txt
WebHarvester-0.1.1.dist-info/RECORD
