Metadata-Version: 2.1
Name: WebHarvester
Version: 0.1.1
Summary: A simple super fast asynchronous crawler framework
Home-page: https://gitee.com/uraurara/web-harvester
Author: ulala
Author-email: 2713389652@qq.com
Classifier: Programming Language :: Python :: 3
Classifier: License :: OSI Approved :: MIT License
Classifier: Operating System :: OS Independent
Requires-Python: >=3.10
License-File: LICENSE
Requires-Dist: aiohttp ==3.9.5
Requires-Dist: aiosignal ==1.3.1
Requires-Dist: async-timeout ==4.0.3
Requires-Dist: attrs ==23.2.0
Requires-Dist: cssselect ==1.2.0
Requires-Dist: frozenlist ==1.4.1
Requires-Dist: idna ==3.7
Requires-Dist: jmespath ==1.0.1
Requires-Dist: lxml ==5.2.2
Requires-Dist: multidict ==6.0.5
Requires-Dist: packaging ==24.0
Requires-Dist: parsel ==1.9.1
Requires-Dist: w3lib ==2.2.0
Requires-Dist: yarl ==1.9.4
